Metadata-Version: 2.1
Name: odoo10-addon-product-search-multi-value
Version: 10.0.1.0.1.99.dev6
Summary: Product Search Multi Value
Home-page: https://github.com/shopinvader/odoo-pim
Author: ACSONE SA/NV
License: AGPL-3
Platform: UNKNOWN
Classifier: Programming Language :: Python
Classifier: Framework :: Odoo
Classifier: Framework :: Odoo :: 10.0
Classifier: License :: OSI Approved :: GNU Affero General Public License v3
Requires-Python: ~=2.7
Requires-Dist: odoo <10.1dev,>=10.0
